setup.cfg
setup.py
summary_smt/__init__.py
summary_smt.egg-info/PKG-INFO
summary_smt.egg-info/SOURCES.txt
summary_smt.egg-info/dependency_links.txt
summary_smt.egg-info/not-zip-safe
summary_smt.egg-info/top_level.txt