Metadata-Version: 2.1
Name: summary-smt
Version: 0.0
Summary: Резюме на python
Author-email: smt_razrab@mail.ru
